contact/__main__.py
contact/localisations/en.ini
contact/localisations/ru.ini
contact/message_handlers/rx_handler.py
contact/message_handlers/tx_handler.py
contact/settings.py
contact/ui/colors.py
contact/ui/contact_ui.py
contact/ui/control_ui.py
contact/ui/default_config.py
contact/ui/dialog.py
contact/ui/menus.py
contact/ui/nav_utils.py
contact/ui/splash.py
contact/ui/ui_state.py
contact/ui/user_config.py
contact/utilities/arg_parser.py
contact/utilities/config_io.py
contact/utilities/control_utils.py
contact/utilities/db_handler.py
contact/utilities/i18n.py
contact/utilities/ini_utils.py
contact/utilities/input_handlers.py
contact/utilities/interfaces.py
contact/utilities/save_to_radio.py
contact/utilities/singleton.py
contact/utilities/telemetry_beautifier.py
contact/utilities/utils.py
contact/utilities/validation_rules.py
contact-1.4.13.dist-info/METADATA
contact-1.4.13.dist-info/WHEEL
contact-1.4.13.dist-info/entry_points.txt
contact-1.4.13.dist-info/licenses/LICENSE
contact-1.4.13.dist-info/RECORD
