Metadata-Version: 2.4
Name: contact
Version: 1.4.13
Summary: This Python curses client for Meshtastic is a terminal-based client designed to manage device settings, enable mesh chat communication, and handle configuration backups and restores.
License-Expression: GPL-3.0-only
License-File: LICENSE
Author: Ben Lipsey
Author-email: ben@pdxlocations.com
Requires-Python: >=3.9,<3.15
Classifier: Programming Language :: Python :: 3
Classifier: Programming Language :: Python :: 3.9
Classifier: Programming Language :: Python :: 3.10
Classifier: Programming Language :: Python :: 3.11
Classifier: Programming Language :: Python :: 3.12
Classifier: Programming Language :: Python :: 3.13
Classifier: Programming Language :: Python :: 3.14
Requires-Dist: meshtastic (>=2.7.5,<3.0.0)
Project-URL: Homepage, https://github.com/pdxlocations/contact
Project-URL: Issues, https://github.com/pdxlocations/contact/issues
